bq/__init__.py
bq/queue.py
bq-0.8.0.dist-info/METADATA
bq-0.8.0.dist-info/RECORD
bq-0.8.0.dist-info/WHEEL
bq-0.8.0.dist-info/top_level.txt
