Metadata-Version: 2.1
Name: bq
Version: 0.8.0
Summary: Queue library
Home-page: https://github.com/BlackEarth/bq
Author: Sean Harrison
Author-email: sah@blackearthgroup.com
License: LGPL 3.0
Platform: UNKNOWN
Classifier: Development Status :: 3 - Alpha
Classifier: Intended Audience :: Developers
Classifier: License :: OSI Approved :: GNU Library or Lesser General Public License (LGPL)
Classifier: Programming Language :: Python :: 3
Provides-Extra: dev
Provides-Extra: test
Requires-Dist: bl
Requires-Dist: bf
Provides-Extra: dev
Provides-Extra: test
